kubeyard/__init__.py
kubeyard/ascii_art.py
kubeyard/base_command.py
kubeyard/context_factories.py
kubeyard/dependencies.py
kubeyard/files_generator.py
kubeyard/io_utils.py
kubeyard/kubernetes.py
kubeyard/logging.py
kubeyard/minikube.py
kubeyard/settings.py
kubeyard/commands/__init__.py
kubeyard/commands/bash_completion.py
kubeyard/commands/build.py
kubeyard/commands/custom_script.py
kubeyard/commands/debug.py
kubeyard/commands/deploy.py
kubeyard/commands/dev_requirements.py
kubeyard/commands/devel.py
kubeyard/commands/fix_code_style.py
kubeyard/commands/global_commands.py
kubeyard/commands/init.py
kubeyard/commands/push.py
kubeyard/commands/shell.py
kubeyard/commands/test.py
kubeyard/commands/update_requirements.py
kubeyard/definitions/dev_requirements/cassandra.yaml
kubeyard/definitions/dev_requirements/cockroachdb.yaml
kubeyard/definitions/dev_requirements/elasticsearch.yaml
kubeyard/definitions/dev_requirements/postgres.yaml
kubeyard/definitions/dev_requirements/pubsub-emulator.yaml
kubeyard/definitions/dev_requirements/rabbitmq.yaml
kubeyard/definitions/dev_requirements/redis.yaml
kubeyard/entrypoints/__init__.py
kubeyard/entrypoints/custom_command_loader.py
kubeyard/entrypoints/kubeyard.py
kubeyard/templates/kubeyard-completion.sh
kubeyard/templates/new_repositories/django/config/kubeyard.yml.template
kubeyard/templates/new_repositories/django/config/kubernetes/deploy/01_service.yml.template
kubeyard/templates/new_repositories/django/config/kubernetes/deploy/02_deployment.yml.template
kubeyard/templates/new_repositories/django/config/kubernetes/deploy/03_ingress.yml.template
kubeyard/templates/new_repositories/django/config/kubernetes/dev_secrets/secrets.yml
kubeyard/templates/new_repositories/django/config/kubernetes/development_overrides/02_deployment.yml.template
kubeyard/templates/new_repositories/django/docker/Dockerfile.template
kubeyard/templates/new_repositories/django/docker/requirements/python.txt
kubeyard-1.1.0.dist-info/LICENSE
kubeyard-1.1.0.dist-info/METADATA
kubeyard-1.1.0.dist-info/WHEEL
kubeyard-1.1.0.dist-info/entry_points.txt
kubeyard-1.1.0.dist-info/top_level.txt
kubeyard-1.1.0.dist-info/RECORD
