Metadata-Version: 2.1
Name: kubeyard
Version: 1.1.0
Summary: A utility to develop, test and deploy Kubernetes microservices.
Home-page: https://github.com/socialwifi/kubeyard
Author: Social WiFi
Author-email: it@socialwifi.com
License: BSD
Classifier: Environment :: Console
Classifier: Intended Audience :: Developers
Classifier: License :: OSI Approved :: BSD License
Classifier: Programming Language :: Python
Classifier: Programming Language :: Python :: 3
Classifier: Programming Language :: Python :: 3.9
Classifier: Programming Language :: Python :: 3.10
Classifier: Programming Language :: Python :: 3.11
Classifier: Programming Language :: Python :: 3.12
License-File: LICENSE
Requires-Dist: click
Requires-Dist: colorlog
Requires-Dist: jinja2
Requires-Dist: kubepy >=1.20.0
Requires-Dist: pyYAML
Requires-Dist: cached-property
Requires-Dist: sh <2
Requires-Dist: pyfiglet
Requires-Dist: termcolor
